{
  "channel": "FSN",
  "date": "2026-06-01",
  "label": "tomorrow",
  "fetchedAt": 1780246973514,
  "fetchedAtIST": "31/5/2026, 10:32:53 pm",
  "events": [
    {
      "eventId": 177080610,
      "programTitle": "FOX SPORTS News",
      "channelId": 126,
      "scheduledDate": 1780250400000,
      "duration": 30,
      "episodeTitle": "31/5/26",
      "parentalRating": "NC",
      "premiereInd": false,
      "seriesNumber": "2026",
      "displaySepNum": false,
      "versionNum": 2608891,
      "imageUrl": "https://images1.resources.foxtel.com.au/store2/mount1/16/4/okdfp8.jpg",
      "placeholder": false,
      "isMovie": false,
      "adultsOnly": false
    },
    {
      "eventId": 177080611,
      "programTitle": "FOX SPORTS News",
      "channelId": 126,
      "scheduledDate": 1780252200000,
      "duration": 30,
      "episodeTitle": "31/5/26",
      "parentalRating": "NC",
      "premiereInd": false,
      "seriesNumber": "2026",
      "displaySepNum": false,
      "versionNum": 2608891,
      "imageUrl": "https://images1.resources.foxtel.com.au/store2/mount1/16/4/okdfp8.jpg",
      "placeholder": false,
      "isMovie": false,
      "adultsOnly": false
    },
    {
      "eventId": 177080612,
      "programTitle": "FOX SPORTS News",
      "channelId": 126,
      "scheduledDate": 1780254000000,
      "duration": 30,
      "episodeTitle": "31/5/26",
      "parentalRating": "NC",
      "premiereInd": false,
      "seriesNumber": "2026",
      "displaySepNum": false,
      "versionNum": 2608891,
      "imageUrl": "https://images1.resources.foxtel.com.au/store2/mount1/16/4/okdfp8.jpg",
      "placeholder": false,
      "isMovie": false,
      "adultsOnly": false
    },
    {
      "eventId": 177080613,
      "programTitle": "FOX SPORTS News",
      "channelId": 126,
      "scheduledDate": 1780255800000,
      "duration": 30,
      "episodeTitle": "31/5/26",
      "parentalRating": "NC",
      "premiereInd": false,
      "seriesNumber": "2026",
      "displaySepNum": false,
      "versionNum": 2608891,
      "imageUrl": "https://images1.resources.foxtel.com.au/store2/mount1/16/4/okdfp8.jpg",
      "placeholder": false,
      "isMovie": false,
      "adultsOnly": false
    },
    {
      "eventId": 177080614,
      "programTitle": "FOX SPORTS News",
      "channelId": 126,
      "scheduledDate": 1780257600000,
      "duration": 30,
      "episodeTitle": "31/5/26",
      "parentalRating": "NC",
      "premiereInd": false,
      "seriesNumber": "2026",
      "displaySepNum": false,
      "versionNum": 2608891,
      "imageUrl": "https://images1.resources.foxtel.com.au/store2/mount1/16/4/okdfp8.jpg",
      "placeholder": false,
      "isMovie": false,
      "adultsOnly": false
    },
    {
      "eventId": 177080615,
      "programTitle": "FOX SPORTS News",
      "channelId": 126,
      "scheduledDate": 1780259400000,
      "duration": 30,
      "episodeTitle": "31/5/26",
      "parentalRating": "NC",
      "premiereInd": false,
      "seriesNumber": "2026",
      "displaySepNum": false,
      "versionNum": 2608891,
      "imageUrl": "https://images1.resources.foxtel.com.au/store2/mount1/16/4/okdfp8.jpg",
      "placeholder": false,
      "isMovie": false,
      "adultsOnly": false
    },
    {
      "eventId": 177080616,
      "programTitle": "Live: FOX SPORTS News",
      "channelId": 126,
      "scheduledDate": 1780261200000,
      "duration": 30,
      "episodeTitle": "1/6/26",
      "parentalRating": "NC",
      "premiereInd": false,
      "seriesNumber": "2026",
      "displaySepNum": false,
      "versionNum": 2608891,
      "imageUrl": "https://images1.resources.foxtel.com.au/store2/mount1/16/4/okdfp8.jpg",
      "placeholder": false,
      "isMovie": false,
      "adultsOnly": false
    },
    {
      "eventId": 177080617,
      "programTitle": "FOX SPORTS News",
      "channelId": 126,
      "scheduledDate": 1780263000000,
      "duration": 30,
      "episodeTitle": "1/6/26",
      "parentalRating": "NC",
      "premiereInd": false,
      "seriesNumber": "2026",
      "displaySepNum": false,
      "versionNum": 2608891,
      "imageUrl": "https://images1.resources.foxtel.com.au/store2/mount1/16/4/okdfp8.jpg",
      "placeholder": false,
      "isMovie": false,
      "adultsOnly": false
    },
    {
      "eventId": 177080618,
      "programTitle": "Live: FOX SPORTS News",
      "channelId": 126,
      "scheduledDate": 1780264800000,
      "duration": 30,
      "episodeTitle": "1/6/26",
      "parentalRating": "NC",
      "premiereInd": false,
      "seriesNumber": "2026",
      "displaySepNum": false,
      "versionNum": 2608891,
      "imageUrl": "https://images1.resources.foxtel.com.au/store2/mount1/16/4/okdfp8.jpg",
      "placeholder": false,
      "isMovie": false,
      "adultsOnly": false
    },
    {
      "eventId": 177080619,
      "programTitle": "FOX SPORTS News",
      "channelId": 126,
      "scheduledDate": 1780266600000,
      "duration": 30,
      "episodeTitle": "1/6/26",
      "parentalRating": "NC",
      "premiereInd": false,
      "seriesNumber": "2026",
      "displaySepNum": false,
      "versionNum": 2608891,
      "imageUrl": "https://images1.resources.foxtel.com.au/store2/mount1/16/4/okdfp8.jpg",
      "placeholder": false,
      "isMovie": false,
      "adultsOnly": false
    },
    {
      "eventId": 177080620,
      "programTitle": "Live: FOX SPORTS News",
      "channelId": 126,
      "scheduledDate": 1780268400000,
      "duration": 30,
      "episodeTitle": "1/6/26",
      "parentalRating": "NC",
      "premiereInd": false,
      "seriesNumber": "2026",
      "displaySepNum": false,
      "versionNum": 2608891,
      "imageUrl": "https://images1.resources.foxtel.com.au/store2/mount1/16/4/okdfp8.jpg",
      "placeholder": false,
      "isMovie": false,
      "adultsOnly": false
    },
    {
      "eventId": 177080621,
      "programTitle": "FOX SPORTS News",
      "channelId": 126,
      "scheduledDate": 1780270200000,
      "duration": 30,
      "episodeTitle": "1/6/26",
      "parentalRating": "NC",
      "premiereInd": false,
      "seriesNumber": "2026",
      "displaySepNum": false,
      "versionNum": 2608891,
      "imageUrl": "https://images1.resources.foxtel.com.au/store2/mount1/16/4/okdfp8.jpg",
      "placeholder": false,
      "isMovie": false,
      "adultsOnly": false
    },
    {
      "eventId": 177080622,
      "programTitle": "Live: FOX SPORTS News",
      "channelId": 126,
      "scheduledDate": 1780272000000,
      "duration": 30,
      "episodeTitle": "1/6/26",
      "parentalRating": "NC",
      "premiereInd": false,
      "seriesNumber": "2026",
      "displaySepNum": false,
      "versionNum": 2608891,
      "imageUrl": "https://images1.resources.foxtel.com.au/store2/mount1/16/4/okdfp8.jpg",
      "placeholder": false,
      "isMovie": false,
      "adultsOnly": false
    },
    {
      "eventId": 177080623,
      "programTitle": "FOX SPORTS News",
      "channelId": 126,
      "scheduledDate": 1780273800000,
      "duration": 30,
      "episodeTitle": "1/6/26",
      "parentalRating": "NC",
      "premiereInd": false,
      "seriesNumber": "2026",
      "displaySepNum": false,
      "versionNum": 2608891,
      "imageUrl": "https://images1.resources.foxtel.com.au/store2/mount1/16/4/okdfp8.jpg",
      "placeholder": false,
      "isMovie": false,
      "adultsOnly": false
    },
    {
      "eventId": 177080624,
      "programTitle": "Live: FOX SPORTS News",
      "channelId": 126,
      "scheduledDate": 1780275600000,
      "duration": 30,
      "episodeTitle": "1/6/26",
      "parentalRating": "NC",
      "premiereInd": false,
      "seriesNumber": "2026",
      "displaySepNum": false,
      "versionNum": 2608891,
      "imageUrl": "https://images1.resources.foxtel.com.au/store2/mount1/16/4/okdfp8.jpg",
      "placeholder": false,
      "isMovie": false,
      "adultsOnly": false
    },
    {
      "eventId": 177080625,
      "programTitle": "FOX SPORTS News",
      "channelId": 126,
      "scheduledDate": 1780277400000,
      "duration": 30,
      "episodeTitle": "1/6/26",
      "parentalRating": "NC",
      "premiereInd": false,
      "seriesNumber": "2026",
      "displaySepNum": false,
      "versionNum": 2608891,
      "imageUrl": "https://images1.resources.foxtel.com.au/store2/mount1/16/4/okdfp8.jpg",
      "placeholder": false,
      "isMovie": false,
      "adultsOnly": false
    },
    {
      "eventId": 177080626,
      "programTitle": "Live: FOX SPORTS News",
      "channelId": 126,
      "scheduledDate": 1780279200000,
      "duration": 30,
      "episodeTitle": "1/6/26",
      "parentalRating": "NC",
      "premiereInd": false,
      "seriesNumber": "2026",
      "displaySepNum": false,
      "versionNum": 2608891,
      "imageUrl": "https://images1.resources.foxtel.com.au/store2/mount1/16/4/okdfp8.jpg",
      "placeholder": false,
      "isMovie": false,
      "adultsOnly": false
    },
    {
      "eventId": 177080627,
      "programTitle": "FOX SPORTS News",
      "channelId": 126,
      "scheduledDate": 1780281000000,
      "duration": 30,
      "episodeTitle": "1/6/26",
      "parentalRating": "NC",
      "premiereInd": false,
      "seriesNumber": "2026",
      "displaySepNum": false,
      "versionNum": 2608891,
      "imageUrl": "https://images1.resources.foxtel.com.au/store2/mount1/16/4/okdfp8.jpg",
      "placeholder": false,
      "isMovie": false,
      "adultsOnly": false
    },
    {
      "eventId": 177311984,
      "programTitle": "Bounce",
      "channelId": 126,
      "scheduledDate": 1780282800000,
      "duration": 60,
      "episodeTitle": "Episode 12",
      "parentalRating": "NC",
      "premiereInd": false,
      "seriesNumber": "2026",
      "displaySepNum": false,
      "versionNum": 2608891,
      "imageUrl": "https://images1.resources.foxtel.com.au/store2/mount1/16/4/io41xi.png",
      "placeholder": false,
      "isMovie": false,
      "adultsOnly": false
    },
    {
      "eventId": 177312635,
      "programTitle": "First Crack",
      "channelId": 126,
      "scheduledDate": 1780286400000,
      "duration": 60,
      "episodeTitle": "Episode 10",
      "parentalRating": "NC",
      "premiereInd": false,
      "seriesNumber": "2026",
      "displaySepNum": false,
      "versionNum": 2608891,
      "imageUrl": "https://images1.resources.foxtel.com.au/store2/mount1/16/4/hu7bg6.png",
      "placeholder": false,
      "isMovie": false,
      "adultsOnly": false
    },
    {
      "eventId": 177312636,
      "programTitle": "Sunday Night with Matty Johns",
      "channelId": 126,
      "scheduledDate": 1780290000000,
      "duration": 60,
      "episodeTitle": "Episode 13",
      "parentalRating": "NC",
      "premiereInd": false,
      "seriesNumber": "2026",
      "displaySepNum": false,
      "versionNum": 2608891,
      "imageUrl": "https://images1.resources.foxtel.com.au/store2/mount1/16/4/xvo9o.png",
      "placeholder": false,
      "isMovie": false,
      "adultsOnly": false
    },
    {
      "eventId": 177312637,
      "programTitle": "AFL Mini: Round 12 MEL v GWS",
      "channelId": 126,
      "scheduledDate": 1780293600000,
      "duration": 20,
      "episodeTitle": "Round 12 MEL v GWS",
      "parentalRating": "NC",
      "premiereInd": false,
      "seriesNumber": "2026",
      "displaySepNum": false,
      "versionNum": 2608891,
      "imageUrl": "https://images1.resources.foxtel.com.au/store2/mount1/16/4/l31nz2.png",
      "placeholder": false,
      "isMovie": false,
      "adultsOnly": false
    },
    {
      "eventId": 177312638,
      "programTitle": "NRL Mini: Round 13 PEN v WAR",
      "channelId": 126,
      "scheduledDate": 1780294800000,
      "duration": 20,
      "episodeTitle": "Round 13 PEN v WAR",
      "parentalRating": "NC",
      "premiereInd": false,
      "seriesNumber": "2026",
      "displaySepNum": false,
      "versionNum": 2608891,
      "imageUrl": "https://images1.resources.foxtel.com.au/store2/mount1/16/4/8c6np4.png",
      "placeholder": false,
      "isMovie": false,
      "adultsOnly": false
    },
    {
      "eventId": 177311985,
      "programTitle": "MotoGP Mini: ITALY",
      "channelId": 126,
      "scheduledDate": 1780296000000,
      "duration": 20,
      "episodeTitle": "ITALY",
      "parentalRating": "NC",
      "premiereInd": false,
      "seriesNumber": "2026",
      "displaySepNum": false,
      "versionNum": 2608891,
      "imageUrl": "https://images1.resources.foxtel.com.au/store2/mount1/16/4/tmk4ef.png",
      "placeholder": false,
      "isMovie": false,
      "adultsOnly": false
    },
    {
      "eventId": 177080640,
      "programTitle": "Live: FOX SPORTS News",
      "channelId": 126,
      "scheduledDate": 1780297200000,
      "duration": 30,
      "episodeTitle": "1/6/26",
      "parentalRating": "NC",
      "premiereInd": false,
      "seriesNumber": "2026",
      "displaySepNum": false,
      "versionNum": 2608891,
      "imageUrl": "https://images1.resources.foxtel.com.au/store2/mount1/16/4/okdfp8.jpg",
      "placeholder": false,
      "isMovie": false,
      "adultsOnly": false
    },
    {
      "eventId": 177080641,
      "programTitle": "Live: AFL Tonight",
      "channelId": 126,
      "scheduledDate": 1780299000000,
      "duration": 30,
      "episodeTitle": "1/6/26",
      "parentalRating": "NC",
      "premiereInd": false,
      "seriesNumber": "2026",
      "displaySepNum": false,
      "versionNum": 2608891,
      "imageUrl": "https://images1.resources.foxtel.com.au/store2/mount1/16/4/a99xxe.png",
      "placeholder": false,
      "isMovie": false,
      "adultsOnly": false
    },
    {
      "eventId": 177080642,
      "programTitle": "Live: NRL Tonight",
      "channelId": 126,
      "scheduledDate": 1780300800000,
      "duration": 30,
      "episodeTitle": "1/6/26",
      "parentalRating": "NC",
      "premiereInd": false,
      "seriesNumber": "2026",
      "displaySepNum": false,
      "versionNum": 2608891,
      "imageUrl": "https://images1.resources.foxtel.com.au/store2/mount1/16/4/aqozar.png",
      "placeholder": false,
      "isMovie": false,
      "adultsOnly": false
    },
    {
      "eventId": 177080643,
      "programTitle": "Live: FOX SPORTS News",
      "channelId": 126,
      "scheduledDate": 1780302600000,
      "duration": 30,
      "episodeTitle": "1/6/26",
      "parentalRating": "NC",
      "premiereInd": false,
      "seriesNumber": "2026",
      "displaySepNum": false,
      "versionNum": 2608891,
      "imageUrl": "https://images1.resources.foxtel.com.au/store2/mount1/16/4/okdfp8.jpg",
      "placeholder": false,
      "isMovie": false,
      "adultsOnly": false
    },
    {
      "eventId": 177080644,
      "programTitle": "Live: FOX SPORTS News",
      "channelId": 126,
      "scheduledDate": 1780304400000,
      "duration": 30,
      "episodeTitle": "1/6/26",
      "parentalRating": "NC",
      "premiereInd": false,
      "seriesNumber": "2026",
      "displaySepNum": false,
      "versionNum": 2608891,
      "imageUrl": "https://images1.resources.foxtel.com.au/store2/mount1/16/4/okdfp8.jpg",
      "placeholder": false,
      "isMovie": false,
      "adultsOnly": false
    },
    {
      "eventId": 177080645,
      "programTitle": "FOX SPORTS News",
      "channelId": 126,
      "scheduledDate": 1780306200000,
      "duration": 30,
      "episodeTitle": "1/6/26",
      "parentalRating": "NC",
      "premiereInd": false,
      "seriesNumber": "2026",
      "displaySepNum": false,
      "versionNum": 2608891,
      "imageUrl": "https://images1.resources.foxtel.com.au/store2/mount1/16/4/okdfp8.jpg",
      "placeholder": false,
      "isMovie": false,
      "adultsOnly": false
    },
    {
      "eventId": 177080646,
      "programTitle": "FOX SPORTS News",
      "channelId": 126,
      "scheduledDate": 1780308000000,
      "duration": 30,
      "episodeTitle": "1/6/26",
      "parentalRating": "NC",
      "premiereInd": false,
      "seriesNumber": "2026",
      "displaySepNum": false,
      "versionNum": 2608891,
      "imageUrl": "",
      "placeholder": false,
      "isMovie": false,
      "adultsOnly": false
    },
    {
      "eventId": 177080647,
      "programTitle": "FOX SPORTS News",
      "channelId": 126,
      "scheduledDate": 1780309800000,
      "duration": 30,
      "episodeTitle": "1/6/26",
      "parentalRating": "NC",
      "premiereInd": false,
      "seriesNumber": "2026",
      "displaySepNum": false,
      "versionNum": 2608891,
      "imageUrl": "",
      "placeholder": false,
      "isMovie": false,
      "adultsOnly": false
    },
    {
      "eventId": 177080648,
      "programTitle": "Live: FOX SPORTS News",
      "channelId": 126,
      "scheduledDate": 1780311600000,
      "duration": 30,
      "episodeTitle": "1/6/26",
      "parentalRating": "NC",
      "premiereInd": false,
      "seriesNumber": "2026",
      "displaySepNum": false,
      "versionNum": 2608891,
      "imageUrl": "",
      "placeholder": false,
      "isMovie": false,
      "adultsOnly": false
    },
    {
      "eventId": 177080649,
      "programTitle": "FOX SPORTS News",
      "channelId": 126,
      "scheduledDate": 1780313400000,
      "duration": 30,
      "episodeTitle": "1/6/26",
      "parentalRating": "NC",
      "premiereInd": false,
      "seriesNumber": "2026",
      "displaySepNum": false,
      "versionNum": 2608891,
      "imageUrl": "",
      "placeholder": false,
      "isMovie": false,
      "adultsOnly": false
    },
    {
      "eventId": 177080650,
      "programTitle": "NRL Tonight",
      "channelId": 126,
      "scheduledDate": 1780315200000,
      "duration": 30,
      "episodeTitle": "1/6/26",
      "parentalRating": "NC",
      "premiereInd": false,
      "seriesNumber": "2026",
      "displaySepNum": false,
      "versionNum": 2608891,
      "imageUrl": "",
      "placeholder": false,
      "isMovie": false,
      "adultsOnly": false
    },
    {
      "eventId": 177080651,
      "programTitle": "AFL Tonight",
      "channelId": 126,
      "scheduledDate": 1780317000000,
      "duration": 30,
      "episodeTitle": "1/6/26",
      "parentalRating": "NC",
      "premiereInd": false,
      "seriesNumber": "2026",
      "displaySepNum": false,
      "versionNum": 2608891,
      "imageUrl": "",
      "placeholder": false,
      "isMovie": false,
      "adultsOnly": false
    },
    {
      "eventId": 177080652,
      "programTitle": "Live: FOX SPORTS News",
      "channelId": 126,
      "scheduledDate": 1780318800000,
      "duration": 30,
      "episodeTitle": "1/6/26",
      "parentalRating": "NC",
      "premiereInd": false,
      "seriesNumber": "2026",
      "displaySepNum": false,
      "versionNum": 2608891,
      "imageUrl": "",
      "placeholder": false,
      "isMovie": false,
      "adultsOnly": false
    },
    {
      "eventId": 177080653,
      "programTitle": "FOX SPORTS News",
      "channelId": 126,
      "scheduledDate": 1780320600000,
      "duration": 30,
      "episodeTitle": "1/6/26",
      "parentalRating": "NC",
      "premiereInd": false,
      "seriesNumber": "2026",
      "displaySepNum": false,
      "versionNum": 2608891,
      "imageUrl": "",
      "placeholder": false,
      "isMovie": false,
      "adultsOnly": false
    },
    {
      "eventId": 177080654,
      "programTitle": "FOX SPORTS News",
      "channelId": 126,
      "scheduledDate": 1780322400000,
      "duration": 30,
      "episodeTitle": "1/6/26",
      "parentalRating": "NC",
      "premiereInd": false,
      "seriesNumber": "2026",
      "displaySepNum": false,
      "versionNum": 2608891,
      "imageUrl": "",
      "placeholder": false,
      "isMovie": false,
      "adultsOnly": false
    },
    {
      "eventId": 177080655,
      "programTitle": "FOX SPORTS News",
      "channelId": 126,
      "scheduledDate": 1780324200000,
      "duration": 30,
      "episodeTitle": "1/6/26",
      "parentalRating": "NC",
      "premiereInd": false,
      "seriesNumber": "2026",
      "displaySepNum": false,
      "versionNum": 2608891,
      "imageUrl": "",
      "placeholder": false,
      "isMovie": false,
      "adultsOnly": false
    },
    {
      "eventId": 177080656,
      "programTitle": "FOX SPORTS News",
      "channelId": 126,
      "scheduledDate": 1780326000000,
      "duration": 30,
      "episodeTitle": "1/6/26",
      "parentalRating": "NC",
      "premiereInd": false,
      "seriesNumber": "2026",
      "displaySepNum": false,
      "versionNum": 2608891,
      "imageUrl": "",
      "placeholder": false,
      "isMovie": false,
      "adultsOnly": false
    },
    {
      "eventId": 177080657,
      "programTitle": "FOX SPORTS News",
      "channelId": 126,
      "scheduledDate": 1780327800000,
      "duration": 30,
      "episodeTitle": "1/6/26",
      "parentalRating": "NC",
      "premiereInd": false,
      "seriesNumber": "2026",
      "displaySepNum": false,
      "versionNum": 2608891,
      "imageUrl": "",
      "placeholder": false,
      "isMovie": false,
      "adultsOnly": false
    },
    {
      "eventId": 177080658,
      "programTitle": "FOX SPORTS News",
      "channelId": 126,
      "scheduledDate": 1780329600000,
      "duration": 30,
      "episodeTitle": "1/6/26",
      "parentalRating": "NC",
      "premiereInd": false,
      "seriesNumber": "2026",
      "displaySepNum": false,
      "versionNum": 2608891,
      "imageUrl": "",
      "placeholder": false,
      "isMovie": false,
      "adultsOnly": false
    },
    {
      "eventId": 177080659,
      "programTitle": "FOX SPORTS News",
      "channelId": 126,
      "scheduledDate": 1780331400000,
      "duration": 30,
      "episodeTitle": "1/6/26",
      "parentalRating": "NC",
      "premiereInd": false,
      "seriesNumber": "2026",
      "displaySepNum": false,
      "versionNum": 2608891,
      "imageUrl": "",
      "placeholder": false,
      "isMovie": false,
      "adultsOnly": false
    },
    {
      "eventId": 177080660,
      "programTitle": "FOX SPORTS News",
      "channelId": 126,
      "scheduledDate": 1780333200000,
      "duration": 30,
      "episodeTitle": "1/6/26",
      "parentalRating": "NC",
      "premiereInd": false,
      "seriesNumber": "2026",
      "displaySepNum": false,
      "versionNum": 2608891,
      "imageUrl": "",
      "placeholder": false,
      "isMovie": false,
      "adultsOnly": false
    },
    {
      "eventId": 177080661,
      "programTitle": "FOX SPORTS News",
      "channelId": 126,
      "scheduledDate": 1780335000000,
      "duration": 30,
      "episodeTitle": "1/6/26",
      "parentalRating": "NC",
      "premiereInd": false,
      "seriesNumber": "2026",
      "displaySepNum": false,
      "versionNum": 2608891,
      "imageUrl": "",
      "placeholder": false,
      "isMovie": false,
      "adultsOnly": false
    },
    {
      "eventId": 177080662,
      "programTitle": "FOX SPORTS News",
      "channelId": 126,
      "scheduledDate": 1780336800000,
      "duration": 30,
      "episodeTitle": "1/6/26",
      "parentalRating": "NC",
      "premiereInd": false,
      "seriesNumber": "2026",
      "displaySepNum": false,
      "versionNum": 2608891,
      "imageUrl": "",
      "placeholder": false,
      "isMovie": false,
      "adultsOnly": false
    },
    {
      "eventId": 177080663,
      "programTitle": "FOX SPORTS News",
      "channelId": 126,
      "scheduledDate": 1780338600000,
      "duration": 30,
      "episodeTitle": "1/6/26",
      "parentalRating": "NC",
      "premiereInd": false,
      "seriesNumber": "2026",
      "displaySepNum": false,
      "versionNum": 2608891,
      "imageUrl": "",
      "placeholder": false,
      "isMovie": false,
      "adultsOnly": false
    }
  ]
}